{
  "release_version": "0.1.0",
  "created_at": "2026-07-09",
  "tome_id": "09_multilingual_regionalization",
  "license_strategy": "Original localization and terminology synthesis supported by selected official public sources for measurement, drug-label and terminology governance. Local resources must be verified at runtime.",
  "sources": {
    "ORIGINAL-MULTI-001": {
      "title": "Original multilingual and regionalization framework for medical RAG",
      "url": "internal://authored-framework/multilingual-regionalization-v0.1",
      "organization": "Generated original synthesis for App_Medica",
      "license_notes": "Original authored synthesis; requires clinical, legal, localization and product review.",
      "used_for": "Translation safety, regional terminology, units, medication names, emergency wording and privacy governance."
    },
    "NIST-SI-001": {
      "title": "NIST SI units and measurement reference",
      "url": "https://www.nist.gov/pml/owm/metric-si",
      "organization": "National Institute of Standards and Technology",
      "license_notes": "Official public reference; final legal review required.",
      "used_for": "Units, measurement normalization and conversion governance."
    },
    "FDA-DRUGFACTS-001": {
      "title": "FDA OTC Drug Facts label framework",
      "url": "https://www.fda.gov/drugs/information-consumers-and-patients-drugs/understanding-over-counter-medicines",
      "organization": "U.S. Food and Drug Administration",
      "license_notes": "Official public reference; final legal review required.",
      "used_for": "Drug Facts, active ingredient and label-driven medication-name normalization."
    },
    "WHO-ICD-001": {
      "title": "WHO International Classification of Diseases overview",
      "url": "https://www.who.int/standards/classifications/classification-of-diseases",
      "organization": "World Health Organization",
      "license_notes": "Official public reference; final legal review required.",
      "used_for": "Controlled terminology and non-diagnostic coding boundary context."
    },
    "HL7-FHIR-001": {
      "title": "HL7 FHIR terminology and localization concepts",
      "url": "https://www.hl7.org/fhir/",
      "organization": "HL7 International",
      "license_notes": "Standards reference; licensing and implementation terms require review.",
      "used_for": "Interoperability, coding, language tags and data-model governance."
    }
  },
  "excluded_sources": [
    {
      "title": "Unverified emergency/crisis/toxicology numbers copied from forums or old pages",
      "reason": "Must be verified at runtime; high risk if stale."
    },
    {
      "title": "Country-specific legal reporting instructions without jurisdiction review",
      "reason": "Requires legal/local review."
    },
    {
      "title": "Commercial medication brand databases copied wholesale",
      "reason": "Licensing and staleness risk; use active-ingredient mapping and runtime label verification."
    },
    {
      "title": "Machine-translated clinical rules without clinical review",
      "reason": "Translation can degrade safety criteria."
    }
  ]
}